<?xml version="1.0" encoding="UTF-8" standalone="yes" ?>
<!DOCTYPE boost_serialization>
<boost_serialization signature="serialization::archive" version="6">
<emission_file class_id="0" tracking_level="0" version="0">
	<z>97</z>
	<a>246</a>
	<s>0</s>
	<discretes class_id="1" tracking_level="0" version="0">
		<count>1</count>
		<item_version>0</item_version>
		<item class_id="2" tracking_level="0" version="0">
			<first>0</first>
			<second class_id="3" tracking_level="0" version="0">
				<count>16</count>
				<item_version>0</item_version>
				<item class_id="4" tracking_level="0" version="0">
					<energy>0.042900000000000001</energy>
					<energy_err>0</energy_err>
					<intensity>0.00181</intensity>
					<intensity_err>0</intensity_err>
					<decay_type>10</decay_type>
				</item>
				<item>
					<energy>0.099500000000000005</energy>
					<energy_err>0</energy_err>
					<intensity>0.002532</intensity>
					<intensity_err>0</intensity_err>
					<decay_type>10</decay_type>
				</item>
				<item>
					<energy>0.10444000000000001</energy>
					<energy_err>0</energy_err>
					<intensity>0.27850000000000003</intensity>
					<intensity_err>0</intensity_err>
					<decay_type>10</decay_type>
				</item>
				<item>
					<energy>0.10929</energy>
					<energy_err>0</energy_err>
					<intensity>0.48110000000000003</intensity>
					<intensity_err>0</intensity_err>
					<decay_type>10</decay_type>
				</item>
				<item>
					<energy>0.123</energy>
					<energy_err>0</energy_err>
					<intensity>0.18990000000000001</intensity>
					<intensity_err>0</intensity_err>
					<decay_type>10</decay_type>
				</item>
				<item>
					<energy>0.127</energy>
					<energy_err>0</energy_err>
					<intensity>0.07596</intensity>
					<intensity_err>0</intensity_err>
					<decay_type>10</decay_type>
				</item>
				<item>
					<energy>0.73450000000000004</energy>
					<energy_err>0</energy_err>
					<intensity>0.031649999999999998</intensity>
					<intensity_err>0</intensity_err>
					<decay_type>10</decay_type>
				</item>
				<item>
					<energy>0.80000000000000004</energy>
					<energy_err>0</energy_err>
					<intensity>0.70009999999999994</intensity>
					<intensity_err>0</intensity_err>
					<decay_type>10</decay_type>
				</item>
				<item>
					<energy>0.83450000000000002</energy>
					<energy_err>0</energy_err>
					<intensity>0.0557</intensity>
					<intensity_err>0</intensity_err>
					<decay_type>10</decay_type>
				</item>
				<item>
					<energy>0.98599999999999999</energy>
					<energy_err>0</energy_err>
					<intensity>0.003545</intensity>
					<intensity_err>0</intensity_err>
					<decay_type>10</decay_type>
				</item>
				<item>
					<energy>1.0369999999999999</energy>
					<energy_err>0</energy_err>
					<intensity>0.019619999999999999</intensity>
					<intensity_err>0</intensity_err>
					<decay_type>10</decay_type>
				</item>
				<item>
					<energy>1.0629999999999999</energy>
					<energy_err>0</energy_err>
					<intensity>0.03671</intensity>
					<intensity_err>0</intensity_err>
					<decay_type>10</decay_type>
				</item>
				<item>
					<energy>1.079</energy>
					<energy_err>0</energy_err>
					<intensity>0.035450000000000002</intensity>
					<intensity_err>0</intensity_err>
					<decay_type>10</decay_type>
				</item>
				<item>
					<energy>1.0820000000000001</energy>
					<energy_err>0</energy_err>
					<intensity>0.070010000000000003</intensity>
					<intensity_err>0</intensity_err>
					<decay_type>10</decay_type>
				</item>
				<item>
					<energy>1.085</energy>
					<energy_err>0</energy_err>
					<intensity>0.0055700000000000003</intensity>
					<intensity_err>0</intensity_err>
					<decay_type>10</decay_type>
				</item>
				<item>
					<energy>1.1240000000000001</energy>
					<energy_err>0</energy_err>
					<intensity>0.053170000000000002</intensity>
					<intensity_err>0</intensity_err>
					<decay_type>10</decay_type>
				</item>
			</second>
		</item>
	</discretes>
	<continuum class_id="5" tracking_level="0" version="0">
		<count>0</count>
		<item_version>0</item_version>
	</continuum>
	<watt class_id="6" tracking_level="0" version="0">
		<count>0</count>
		<item_version>0</item_version>
	</watt>
	<watt_scale class_id="7" tracking_level="0" version="0">
		<count>0</count>
		<item_version>0</item_version>
	</watt_scale>
</emission_file>
</boost_serialization>

